bibscrap/__init__.py
bibscrap/__main__.py
bibscrap-0.0.4.dist-info/LICENSE.rst
bibscrap-0.0.4.dist-info/METADATA
bibscrap-0.0.4.dist-info/WHEEL
bibscrap-0.0.4.dist-info/entry_points.txt
bibscrap-0.0.4.dist-info/top_level.txt
bibscrap-0.0.4.dist-info/RECORD
