Metadata-Version: 2.1
Name: bibscrap
Version: 0.0.4
Summary: Semi-automated tools for systematic literature reviews.
Home-page: https://github.com/cotterell/bibscrap
Author: Michael E. Cotterell
Author-email: mepcotterell@gmail.com
Maintainer: Michael E. Cotterell
Maintainer-email: mepcotterell@gmail.com
License: MIT
Project-URL: Bug Tracker, https://github.com/cotterell/bibscrap/issues
Project-URL: Documentation, https://bibscrap.readthedocs.io/
Project-URL: Source, https://github.com/cotterell/bibscrap
Platform: UNKNOWN
Classifier: Development Status :: 2 - Pre-Alpha
Classifier: License :: OSI Approved :: MIT License
Classifier: Programming Language :: Python
Classifier: Programming Language :: Python :: 3
Classifier: Programming Language :: Python :: 3 :: Only
Classifier: Programming Language :: Python :: 3.9
Classifier: Programming Language :: Python :: 3.10
Classifier: Topic :: Scientific/Engineering
Classifier: Topic :: Utilities
Requires-Python: >=3.9
License-File: LICENSE.rst
Requires-Dist: scrapy
